LICENSE
MANIFEST.in
README.md
requirements.txt
setup.py
smart_utils/__init__.py
smart_utils.egg-info/PKG-INFO
smart_utils.egg-info/SOURCES.txt
smart_utils.egg-info/dependency_links.txt
smart_utils.egg-info/requires.txt
smart_utils.egg-info/top_level.txt
smart_utils/aws/__init__.py
smart_utils/aws/ssm.py
smart_utils/logging/__init__.py
smart_utils/logging/config.py
smart_utils/logging/logger.py
tests/__init__.py
tests/aws/__init__.py
tests/aws/test_aws.py
tests/aws/test_ssm.py
tests/logging/__init__.py
tests/logging/test_config.py
tests/logging/test_logger.py