Metadata-Version: 1.1
Name: smart-utils
Version: 0.1.4
Summary: Utils module
Home-page: https://github.com/smart-protection/smart_python_utils
Author: jc_diaz
Author-email: juancarlos.diaz@smartprotection.com
License: MIT
Keywords: sample setup
Platform: UNKNOWN
Classifier: Development Status :: 4 - Beta
Classifier: Intended Audience :: Developers
Classifier: Topic :: Software Development :: Libraries
Classifier: License :: OSI Approved :: MIT License
Classifier: Operating System :: OS Independent
Classifier: Programming Language :: Python :: 3
Classifier: Programming Language :: Python :: 3.2
Classifier: Programming Language :: Python :: 3.3
Classifier: Programming Language :: Python :: 3.4
Classifier: Programming Language :: Python :: 3.6
Classifier: Programming Language :: Python :: 3.7
